{"1005":{"oid":"1005","type":"food","flag":"","creator":"12943","name":"Smart Balance Butter spread original","upc":"","imagelink":"","description":"","slug":"Smart-Balance-Butter-spread-original","category":"","weight":"0","emissions":"0","embodied":"0","transport":"0","process":null,"endoflife":null,"shipping":"0","lifetime":null,"usagetype":"","usageenergy":null,"usageemissions":null,"timecreated":"2011-04-10 12:20:43","timemodified":"2011-04-10 12:20:43","visibility":"public","showfootprint":"on","showembodied":"on","showtransport":"on","showprocess":"on","showendoflife":"on","showlastleg":"on","showuse":"on","showstats":"on","stops":{"origin":{"related_to":"1005","part_or_object":"o","notes":null,"placename":"Denver, CO, USA","id":"15025","category":"1","lat":"39.7391536","lon":"-104.9847034","name":"origin","hops":{"incoming":[],"outgoing":[]}}},"user":{"name":"ariana.b","id":"12943"}}}