{"2047":{"oid":"2047","type":"food","flag":"","creator":"7261","name":"Pomodori","upc":"","imagelink":"","description":"","slug":"pomodori","category":null,"weight":null,"emissions":"0","embodied":"0","transport":"0","process":"0","endoflife":"0","shipping":"0","lifetime":null,"usagetype":null,"usageenergy":null,"usageemissions":null,"timecreated":"2010-02-24 22:03:35.919767","timemodified":"2009-12-03 10:07:59","visibility":"public","showfootprint":"on","showembodied":"on","showtransport":"on","showprocess":"on","showendoflife":"on","showlastleg":"on","showuse":"on","showstats":"on","stops":{"origin":{"related_to":"2047","part_or_object":"o","notes":"","placename":"Italia","id":"323","category":"1","lat":"41.87194","lon":"12.56738","name":"origin","hops":{"incoming":[],"outgoing":[]}}},"user":{"name":"ludwinas","id":"7261"}}}