{"supplychain":{"attributes":{"title":"Butoir de quai","emissions:total":"0","legacy:emissions":"0","emissions:embodied":"0","emissions:transport":"0","legacy:distance":"0","distance:transport":"0","alias:preferred":"butoir-de-quai","legacy:creator":"7488","legacy:oid":"2277","sm:ui:co2e":1,"sm:ui:weight":1,"description":"Created on February 24, 2010 by vadorsky on Sourcemap.org.","sm:migrated:time":1317317213},"other_perms":1,"stops":[{"geometry":"POINT(261710.686834 6250575.634689)","attributes":{"name":"Butoir de quai","1":"Paris, France","address":"Paris, France","category":"1","title":"Butoir de quai","qty":null,"co2e":0,"weight":null,"unit":"kg","description":""},"local_stop_id":"464"}],"hops":[]}}