{"2531":{"oid":"2531","type":"food","flag":"","creator":"7821","name":"lilium bulb edible","upc":"","imagelink":"","description":"lilium bulb edible which can be served in salad or soup\/congee.","slug":"lilium-bulb-edible","category":"","weight":"0.1","emissions":"0.01","embodied":"0.01","transport":"0","process":"0","endoflife":"0","shipping":"0","lifetime":null,"usagetype":"","usageenergy":null,"usageemissions":null,"timecreated":"2010-02-24 22:03:36.734425","timemodified":"2010-02-12 04:31:17","visibility":"public","showfootprint":"on","showembodied":"on","showtransport":"on","showprocess":"on","showendoflife":"on","showlastleg":"on","showuse":"on","showstats":"on","stops":{"origin":{"related_to":"2531","part_or_object":"o","notes":"","placename":"Lanzhou, Gansu, China","id":"693","category":"1","lat":"36.061255","lon":"103.834377","name":"origin","hops":{"incoming":[],"outgoing":[]}}},"user":{"name":"dongjinc","id":"7821"}}}