{"2543":{"oid":"2543","type":"object","flag":"","creator":"7840","name":"geo10","upc":"","imagelink":"","description":"","slug":"geo10","category":null,"weight":null,"emissions":"0","embodied":"0","transport":"0","process":"0","endoflife":"0","shipping":"0","lifetime":null,"usagetype":null,"usageenergy":null,"usageemissions":null,"timecreated":"2010-02-24 22:03:36.758223","timemodified":"2010-02-15 16:55:33","visibility":"public","showfootprint":"on","showembodied":"on","showtransport":"on","showprocess":"on","showendoflife":"on","showlastleg":"on","showuse":"on","showstats":"on","stops":{"origin":{"related_to":"2543","part_or_object":"o","notes":"","placename":"","id":"700","category":"1","lat":"0","lon":"0","name":"origin","hops":{"incoming":[],"outgoing":[]}}},"user":{"name":"boneal","id":"7840"}}}