{"supplychain":{"attributes":{"title":"test","emissions:total":"0","legacy:emissions":"0","emissions:embodied":"0","emissions:transport":"0","legacy:distance":"0","distance:transport":"0","alias:preferred":"test-37","legacy:creator":"7848","legacy:oid":"2551","sm:ui:co2e":1,"sm:ui:weight":1,"description":"Created on February 24, 2010 by benjamin on Sourcemap.org.","sm:migrated:time":1317317239},"other_perms":1,"stops":[{"geometry":"POINT(-173750.778551 5385665.410672)","attributes":{"name":"test","1":"Biarritz, France","address":"Biarritz, France","category":"1","title":"test","qty":null,"co2e":0,"weight":null,"unit":"kg","description":""},"local_stop_id":"708"}],"hops":[]}}