{"supplychain":{"attributes":{"title":"Lovat Guests 2009","emissions:total":"21777.3","weight":"44329","legacy:emissions":"21777.3","emissions:embodied":"0","emissions:transport":"21777.3","legacy:distance":"48049","distance:transport":"48049","alias:preferred":"lovat-guests-2009","legacy:creator":"6008","legacy:oid":"271","sm:ui:co2e":1,"sm:ui:weight":1,"description":"Created on February 24, 2010 by cazgreg on Sourcemap.org.","sm:migrated:time":1317317244},"other_perms":1,"stops":[{"geometry":"POINT(-492519.917919 7826396.258531)","attributes":{"name":"Lovat Guests 2009","1":"Loch Ness, Highland, UK","address":"Loch Ness, Highland, UK","category":"1","title":"Lovat Guests 2009","qty":"44329","co2e":0,"weight":"44329","unit":"kg","description":""},"local_stop_id":"65"}],"hops":[]}}