{"supplychain":{"attributes":{"title":"Pasta","emissions:total":"4.28329588205","weight":"1.95","legacy:emissions":"0.01279588205","emissions:embodied":"4.2705","emissions:transport":"0.01279588205","legacy:distance":"3902.34","distance:transport":"3902.34","alias:preferred":"pasta-5","legacy:creator":"9244","legacy:oid":"3307","sm:ui:co2e":1,"sm:ui:weight":1,"description":"Created on March 9, 2010 by Rubarb_killer57 on Sourcemap.org:\n\nMy dinner, Pasta","sm:migrated:time":1316470749},"other_perms":1,"stops":[{"geometry":"POINT(-8837293.142330 5414550.997015)","attributes":{"name":"Pasta","1":"Toronto, ON, Canada","address":"Toronto, ON, Canada","category":"1","title":"Pasta","qty":"1.95","co2e":0,"weight":"1.95","unit":"kg","description":"My dinner, Pasta"},"local_stop_id":"1067"},{"geometry":"POINT(-8832469.334836 5424858.779639)","attributes":{"name":"Cheese","1":"Don Mills, Toronto, ON, Canada","address":"Don Mills, Toronto, ON, Canada","title":"Cheese","qty":"0.2","co2e":"2.19","weight":"0.2","unit":"kg","description":""},"local_stop_id":4219},{"geometry":"POINT(-13707722.352814 6319705.689514)","attributes":{"name":"Pasta","1":"Vancouver, BC, Canada","address":"Vancouver, BC, Canada","title":"Pasta","qty":"0.5","co2e":"2.19","weight":"0.5","unit":"kg","description":""},"local_stop_id":4220},{"geometry":"POINT(-8197464.442807 5707803.610438)","attributes":{"name":"Chicken","1":"Montreal, QC, Canada","address":"Montreal, QC, Canada","title":"Chicken","qty":"0.25","co2e":"2.19","weight":"0.25","unit":"kg","description":""},"local_stop_id":4221},{"geometry":"POINT(-8837293.142330 5414550.997015)","attributes":{"name":"Pasta Sauce","1":"Toronto, ON, Canada","address":"Toronto, ON, Canada","title":"Pasta Sauce","qty":"0.5","co2e":"2.19","weight":"0.5","unit":"kg","description":""},"local_stop_id":4222},{"geometry":"POINT(-8878836.017822 5416962.454905)","attributes":{"name":"Nestea","1":"Brampton, ON, Canada","address":"Brampton, ON, Canada","title":"Nestea","qty":"0.5","co2e":"2.19","weight":"0.5","unit":"kg","description":""},"local_stop_id":4223}],"hops":[{"geometry":"MULTILINESTRING((-8832469.334836 5424858.779639, -8837293.142330 5414550.997015))","from_stop_id":"4219","to_stop_id":"1067","attributes":{"co2e":"0.020300","qty":1,"weight":"0.2"}},{"geometry":"MULTILINESTRING((-13707722.352814 6319705.689514, -8837293.142330 5414550.997015))","from_stop_id":"4220","to_stop_id":"1067","attributes":{"co2e":"0.005600","qty":1,"weight":"0.5"}},{"geometry":"MULTILINESTRING((-8197464.442807 5707803.610438, -8837293.142330 5414550.997015))","from_stop_id":"4221","to_stop_id":"1067","attributes":{"co2e":"0.020300","qty":1,"weight":"0.25"}},{"geometry":"MULTILINESTRING((-8837293.142330 5414550.997015, -8837293.142330 5414550.997015))","from_stop_id":"4222","to_stop_id":"1067","attributes":{"co2e":"0.053400","qty":1,"weight":"0.5"}},{"geometry":"MULTILINESTRING((-8878836.017822 5416962.454905, -8837293.142330 5414550.997015))","from_stop_id":"4223","to_stop_id":"1067","attributes":{"co2e":"0.053400","qty":1,"weight":"0.5"}}]}}