{"3706":{"oid":"3706","type":"object","flag":"","creator":"9616","name":"Boston","upc":"","imagelink":"","description":"Digital system","slug":"boston-1","category":null,"weight":"0","emissions":"0","embodied":"0","transport":"0","process":"0","endoflife":"0","shipping":null,"lifetime":null,"usagetype":null,"usageenergy":null,"usageemissions":null,"timecreated":"2010-05-05 10:44:27.584352","timemodified":"2010-05-05 14:44:27","visibility":"public","showfootprint":"on","showembodied":"on","showtransport":"on","showprocess":"on","showendoflife":"on","showlastleg":"on","showuse":"on","showstats":"on","stops":{"origin":{"related_to":"3706","part_or_object":"o","notes":"","placename":"Boston, MA, USA","id":"1456","category":"1","lat":"42.3584308","lon":"-71.0597732","name":"origin","hops":{"incoming":[],"outgoing":[]}}},"user":{"name":"thomas yamaguchi","id":"9616"}}}