{"supplychain":{"attributes":{"title":"Franzoesische Pfanne 1000","emissions:total":"1356.76621262","weight":"700","legacy:emissions":"3.286212618","emissions:embodied":"1353.48","emissions:transport":"3.286212618","legacy:distance":"9973.24","distance:transport":"9973.24","alias:preferred":"frpfanne1000","legacy:creator":"9624","legacy:oid":"3932","sm:ui:co2e":1,"sm:ui:weight":1,"description":"Created on July 21, 2010 by marwolka on Sourcemap.org.","sm:migrated:time":1317317344},"other_perms":1,"stops":[{"geometry":"POINT(1822609.287567 6141730.131215)","attributes":{"name":"Franzoesische Pfanne 1000","1":"Vienna, Austria","address":"Vienna, Austria","category":"1","title":"Franzoesische Pfanne 1000","qty":"700","co2e":0,"weight":"700","unit":"kg","description":""},"local_stop_id":"1697"}],"hops":[]}}