{"3973":{"oid":"3973","type":"trace","flag":"","creator":"10378","name":"Palm Oil","upc":"","imagelink":"","description":"","slug":"palm-oil-1","category":null,"weight":"0","emissions":"0","embodied":"0","transport":"0","process":"0","endoflife":"0","shipping":null,"lifetime":null,"usagetype":null,"usageenergy":null,"usageemissions":null,"timecreated":"2010-08-16 07:34:44.398041","timemodified":"2010-08-16 11:34:44","visibility":"public","showfootprint":"on","showembodied":"on","showtransport":"on","showprocess":"on","showendoflife":"on","showlastleg":"on","showuse":"on","showstats":"on","stops":{"origin":{"related_to":"3973","part_or_object":"o","notes":"","placename":"","id":"1748","category":"1","lat":"0","lon":"0","name":"origin","hops":{"incoming":[],"outgoing":[]}}},"user":{"name":"curranm","id":"10378"}}}