{"supplychain":{"attributes":{"title":"Vehicle BMW Z4 - 2002","emissions:total":"0","weight":"0","legacy:emissions":"0","emissions:embodied":"0","emissions:transport":"0","alias:preferred":"vehicle-bmw-z4-2002","legacy:creator":"10651","legacy:oid":"4151","description":"Created on September 21, 2010 by Carlochiulli on Sourcemap.org.","sm:migrated:time":1317317367},"other_perms":1,"stops":[{"geometry":"POINT(0.000000 -0.000000)","attributes":{"name":"Vehicle BMW Z4 - 2002","1":"","address":"","category":"1","title":"Vehicle BMW Z4 - 2002","qty":"0","co2e":0,"weight":"0","unit":"kg","description":""},"local_stop_id":"1934"}],"hops":[]}}