{"supplychain":{"attributes":{"title":"Nike Factory Locations ","emissions:total":"0","weight":"0","legacy:emissions":"0","emissions:embodied":"0","emissions:transport":"0","alias:preferred":"nike-factory-locations-","legacy:creator":"10866","legacy:oid":"4223","sm:ui:co2e":1,"sm:ui:weight":1,"description":"Created on October 10, 2010 by ctki223 on Sourcemap.org:\n\nThese are all the Nike factory locations in the year 2009. From http:\/\/www.nikebiz.com.\/responsibility\/workers_and_factories.html","sm:migrated:time":1317317374},"other_perms":1,"stops":[{"geometry":"POINT(-13701954.734149 5473503.535399)","attributes":{"name":"Nike Factory Locations ","1":"Eugene, OR, USA","address":"Eugene, OR, USA","category":"1","title":"Nike Factory Locations ","qty":"0","co2e":0,"weight":"0","unit":"kg","description":"These are all the Nike factory locations in the year 2009. From http:\/\/www.nikebiz.com.\/responsibility\/workers_and_factories.html"},"local_stop_id":"2010"}],"hops":[]}}