{"supplychain":{"attributes":{"title":"AES0015","emissions:total":"1254.99112688","weight":"23.936","legacy:emissions":"0.674633881","emissions:embodied":"77.88968","emissions:transport":"0.674633881","legacy:distance":"7980.54","distance:transport":"7980.54","alias:preferred":"aes0015","legacy:creator":"11046","legacy:oid":"4331","sm:ui:co2e":1,"sm:ui:weight":1,"description":"Created on October 28, 2010 by aes_solar on Sourcemap.org:\n\n2.5M2, Type G, Portrait Header and Riser Collector","sm:migrated:time":1317317386},"other_perms":0,"stops":[{"geometry":"POINT(-402668.012439 7886235.570302)","attributes":{"name":"AES0015","1":"Lea Rd, Forres, Moray IV36 1, UK","address":"Lea Rd, Forres, Moray IV36 1, UK","category":"1","title":"AES0015","qty":"23.936","co2e":0,"weight":"23.936","unit":"kg","description":"2.5M2, Type G, Portrait Header and Riser Collector"},"local_stop_id":"7462"}],"hops":[]}}