{"4405":{"oid":"4405","type":"food","flag":"","creator":"11224","name":"Dole Banana ","upc":"","imagelink":"","description":"The trip of a Banana from Ecuador to the Grocery Store ","slug":"dole-banana-","category":null,"weight":"0","emissions":"0","embodied":"0","transport":"0","process":"0","endoflife":"0","shipping":null,"lifetime":null,"usagetype":null,"usageenergy":null,"usageemissions":null,"timecreated":"2010-11-12 10:44:53.91375","timemodified":"2010-11-12 15:44:53","visibility":"public","showfootprint":"on","showembodied":"on","showtransport":"on","showprocess":"on","showendoflife":"on","showlastleg":"on","showuse":"on","showstats":"on","stops":{"origin":{"related_to":"4405","part_or_object":"o","notes":"","placename":"Berkeley, CA, USA","id":"2143","category":"1","lat":"37.8715926","lon":"-122.272747","name":"origin","hops":{"incoming":[],"outgoing":[]}}},"user":{"name":"meagan_wodecki","id":"11224"}}}