{"supplychain":{"attributes":{"title":"Lasagna","emissions:total":"0","weight":"0","legacy:emissions":"0","emissions:embodied":"0","emissions:transport":"0","legacy:distance":"0","distance:transport":"0","alias:preferred":"Lasagna","legacy:creator":"12316","legacy:oid":"468","sm:ui:co2e":1,"sm:ui:weight":1,"description":"Created on February 11, 2011 by timothytjl on Sourcemap.org:\n\nLasagna","sm:migrated:time":1317317397},"other_perms":1,"stops":[{"geometry":"POINT(-8516150.404252 5227716.456729)","attributes":{"name":"Lasagna","1":"Ithaca, NY, USA","address":"Ithaca, NY, USA","category":"1","title":"Lasagna","qty":"0","co2e":0,"weight":"0","unit":"kg","description":"Lasagna"},"local_stop_id":"10619"}],"hops":[]}}