{"559":{"oid":"559","type":"object","flag":"","creator":"6213","name":"Pine Oil","upc":"","imagelink":"","description":"pine oil","slug":"pine-oil","category":"","weight":"0","emissions":"0","embodied":"0","transport":"0","process":"0","endoflife":"0","shipping":"0","lifetime":"0","usagetype":"","usageenergy":"0","usageemissions":"0","timecreated":"2010-02-24 22:03:35.540634","timemodified":"2009-10-05 15:30:03","visibility":"private","showfootprint":"on","showembodied":"on","showtransport":"on","showprocess":"on","showendoflife":"on","showlastleg":"on","showuse":"on","showstats":"on","stops":{"origin":{"related_to":"559","part_or_object":"o","notes":"","placename":"China","id":"102","category":"1","lat":"0","lon":"0","name":"origin","hops":{"incoming":[{"transport_id":"17","id":"728","transport_name":"None Selected","transport_description":null,"transport_unit":"kg km","transport_co2_eq":"0.000000","from_stop_id":"2979","from_stop_lat":"0","from_stop_lon":"0","to_stop_id":"102","to_stop_name":"origin","to_stop_lat":"0","placename":"Part Location","to_stop_lon":"0","to_stop":{"id":"102","name":"origin","lat":"0","placename":"China","lon":"0"},"from_stop":{"name":"origin","id":"2979","lat":"0","lon":"0","placename":"Part Location"}}],"outgoing":[]}}},"parts":[{"oid":"559","imid":"905","linkid":"","weight":"0","rawemissions":"0","emissions":"0","shipping":"0","processemissions":null,"endoflifeemissions":null,"disposaltype":null,"disposalenergy":null,"disposalimpact":null,"disposalemissions":null,"description":"","name":"TTT Spring 2008","id":"905","stops":{"origin":{"related_to":"905","part_or_object":"p","notes":"","placename":"Part Location","id":2979,"name":"origin","lat":"0","lon":"0","hops":{"incoming":[],"outgoing":[{"transport_id":"17","id":"728","transport_name":"None Selected","transport_description":null,"transport_unit":"kg km","transport_co2_eq":"0.000000","from_stop_id":"2979","from_stop_lat":"0","from_stop_lon":"0","from_stop_placename":"Part Location","to_stop_id":"102","to_stop_name":"origin","to_stop_lat":"0","to_stop_lon":"0","to_stop_placename":"China","to_stop":{"id":"102","name":"origin","lat":"0","lon":"0","placename":"China"},"from_stop":{"name":"origin","id":"2979","lat":"0","lon":"0","placename":"Part Location"}}]}}},"processes":[],"eols":[]}],"user":{"name":"dtracz","id":"6213"}}}