{"767":{"oid":"767","type":"food","flag":"","creator":"12743","name":"Fruit Cup","upc":"","imagelink":"","description":"","slug":"Fruit-Cup","category":"","weight":"0","emissions":"0","embodied":"0","transport":"0","process":null,"endoflife":null,"shipping":"0","lifetime":null,"usagetype":"","usageenergy":null,"usageemissions":null,"timecreated":"2011-03-24 22:00:42","timemodified":"2011-03-24 22:00:42","visibility":"public","showfootprint":"on","showembodied":"on","showtransport":"on","showprocess":"on","showendoflife":"on","showlastleg":"on","showuse":"on","showstats":"on","stops":{"origin":{"related_to":"767","part_or_object":"o","notes":null,"placename":"Austin, TX, USA","id":"13820","category":"1","lat":"30.267153","lon":"-97.7430608","name":"origin","hops":{"incoming":[],"outgoing":[]}}},"user":{"name":"jlassier90","id":"12743"}}}