{"851":{"oid":"851","type":"trace","flag":"","creator":"12369","name":"KSEA Transportation","upc":"","imagelink":"","description":"Provider of marine transportation and distribution of refined petroleum products","slug":"KSEA-Transportation","category":"","weight":"0","emissions":"0","embodied":"0","transport":"0","process":null,"endoflife":null,"shipping":"0","lifetime":null,"usagetype":"","usageenergy":null,"usageemissions":null,"timecreated":"2011-04-06 11:34:30","timemodified":"2011-04-06 11:34:30","visibility":"public","showfootprint":"on","showembodied":"on","showtransport":"on","showprocess":"on","showendoflife":"on","showlastleg":"on","showuse":"on","showstats":"on","stops":{"origin":{"related_to":"851","part_or_object":"o","notes":null,"placename":"East Brunswick, NJ, USA","id":"14186","category":"1","lat":"40.4278841","lon":"-74.415984","name":"origin","hops":{"incoming":[],"outgoing":[]}}},"user":{"name":"erinh","id":"12369"}}}